{
    "client": "Thunder Client",
    "collectionName": "ForgottenKingdom",
    "dateExported": "2024-03-14T10:12:52.251Z",
    "version": "1.1",
    "folders": [
        {
            "_id": "d7b450d1-ef99-4331-ae6c-7c7a1015f915",
            "name": "User",
            "containerId": "",
            "created": "2024-03-14T09:15:39.729Z",
            "sortNum": 10000
        },
        {
            "_id": "95b450e7-cbec-4a87-b49a-7b75ded22a02",
            "name": "Player",
            "containerId": "",
            "created": "2024-03-14T09:15:39.730Z",
            "sortNum": 20000
        },
        {
            "_id": "03986ae3-a804-48c9-a1f9-2e6b1656addf",
            "name": "Enemy",
            "containerId": "",
            "created": "2024-03-14T09:15:39.731Z",
            "sortNum": 30000
        },
        {
            "_id": "18c3cb4b-5925-4867-9f4a-5b5272c5a4cc",
            "name": "Resident",
            "containerId": "",
            "created": "2024-03-14T09:15:39.732Z",
            "sortNum": 40000
        },
        {
            "_id": "13e3b6fa-51af-4d5c-9c3b-986ab6e05164",
            "name": "Market",
            "containerId": "",
            "created": "2024-03-14T09:15:39.733Z",
            "sortNum": 50000
        },
        {
            "_id": "c22de10b-9f3f-4a28-a28d-568b52483553",
            "name": "Building",
            "containerId": "",
            "created": "2024-03-14T09:15:39.734Z",
            "sortNum": 60000
        },
        {
            "_id": "59e75d3b-30ca-4737-81aa-b66518ab8e69",
            "name": "Tool",
            "containerId": "",
            "created": "2024-03-14T09:15:39.735Z",
            "sortNum": 70000
        },
        {
            "_id": "4ba0a9fc-7116-4b07-9207-72b5f183085d",
            "name": "Quest",
            "containerId": "",
            "created": "2024-03-14T09:15:39.736Z",
            "sortNum": 80000
        }
    ],
    "requests": [
        {
            "_id": "dfbaa6fc-452a-4882-b281-28dafe84672e",
            "colId": "ce622ca6-536d-4f71-81ba-0a3ef36cbb55",
            "containerId": "95b450e7-cbec-4a87-b49a-7b75ded22a02",
            "name": "getAllData",
            "url": "http://localhost:3000/player",
            "method": "GET",
            "sortNum": 10000,
            "created": "2024-03-14T09:15:39.733Z",
            "modified": "2024-03-14T09:15:39.733Z",
            "headers": [
                {
                    "name": "Accept",
                    "value": "application/json"
                },
                {
                    "name": "Content-Type",
                    "value": "application/json"
                }
            ],
            "params": [],
            "auth": {
                "type": "bearer",
                "bearer": "eyJhbGciOiJIUzI1NiIsInR5cCI6IkpXVCJ9.eyJpZCI6ImJkOTk3MjAwLWRiY2UtMTFlZS1iNTEwLTM3ZmZkYTJjYTM1OSIsImlhdCI6MTcwOTg4MjAwOCwiZXhwIjoxNzA5ODg1NjA4fQ.U8pnyseFIr59e-ut2C9WNGxztyV37lkOBXTHiyotgMs"
            },
            "tests": []
        },
        {
            "_id": "abf69a37-765f-450b-b5d4-f8ca2ee9013e",
            "colId": "ce622ca6-536d-4f71-81ba-0a3ef36cbb55",
            "containerId": "4ba0a9fc-7116-4b07-9207-72b5f183085d",
            "name": "getQuests",
            "url": "http://localhost:3000/quest?is_active=false&sort_by=is_mainstory",
            "method": "GET",
            "sortNum": 10000,
            "created": "2024-03-14T09:15:39.734Z",
            "modified": "2024-03-14T10:10:55.577Z",
            "headers": [
                {
                    "name": "Accept",
                    "value": "application/json"
                },
                {
                    "name": "Content-Type",
                    "value": "application/json"
                }
            ],
            "params": [
                {
                    "name": "is_active",
                    "value": "false",
                    "isPath": false
                },
                {
                    "name": "sort_by",
                    "value": "is_mainstory",
                    "isPath": false
                }
            ],
            "reqType": "get",
            "auth": {
                "type": "bearer",
                "bearer": "eyJhbGciOiJIUzI1NiIsInR5cCI6IkpXVCJ9.eyJpZCI6IjI5MThiYTIwLWUxZTktMTFlZS1hYWJiLWIxNWIxZTAyYTRhNiIsImlhdCI6MTcxMDQxMDIwNCwiZXhwIjoxNzEwNDEzODA0fQ.azv7RIGn4trrwD4kxdkjwVA6yaumBh8ElsSDB_GZsCM"
            },
            "tests": []
        },
        {
            "_id": "7dc575cf-7789-420b-a0d3-dbe3e5a06ded",
            "colId": "ce622ca6-536d-4f71-81ba-0a3ef36cbb55",
            "containerId": "03986ae3-a804-48c9-a1f9-2e6b1656addf",
            "name": "getAllEnemies",
            "url": "http://localhost:3000/enemies",
            "method": "GET",
            "sortNum": 10000,
            "created": "2024-03-14T09:15:39.739Z",
            "modified": "2024-03-14T09:15:39.739Z",
            "headers": [
                {
                    "name": "Accept",
                    "value": "application/json"
                },
                {
                    "name": "Content-Type",
                    "value": "application/json"
                }
            ],
            "params": [],
            "auth": {
                "type": "bearer",
                "bearer": "eyJhbGciOiJIUzI1NiIsInR5cCI6IkpXVCJ9.eyJpZCI6ImJkOTk3MjAwLWRiY2UtMTFlZS1iNTEwLTM3ZmZkYTJjYTM1OSIsImlhdCI6MTcwOTgwNDY1NywiZXhwIjoxNzA5ODA4MjU3fQ.Wv1eLjJiinKZ8_XD9NPqPkEKcoJ8F02mtNkXQ3GuATA"
            },
            "tests": []
        },
        {
            "_id": "afd65f9b-d79f-4e0a-b1e5-c3ae937c7e63",
            "colId": "ce622ca6-536d-4f71-81ba-0a3ef36cbb55",
            "containerId": "18c3cb4b-5925-4867-9f4a-5b5272c5a4cc",
            "name": "getAllResidents",
            "url": "http://localhost:3000/residents",
            "method": "GET",
            "sortNum": 10000,
            "created": "2024-03-14T09:15:39.744Z",
            "modified": "2024-03-14T09:15:39.744Z",
            "headers": [
                {
                    "name": "Accept",
                    "value": "application/json"
                },
                {
                    "name": "Content-Type",
                    "value": "application/json"
                }
            ],
            "params": [],
            "auth": {
                "type": "bearer",
                "bearer": "eyJhbGciOiJIUzI1NiIsInR5cCI6IkpXVCJ9.eyJpZCI6ImJkOTk3MjAwLWRiY2UtMTFlZS1iNTEwLTM3ZmZkYTJjYTM1OSIsImlhdCI6MTcwOTgwNDY1NywiZXhwIjoxNzA5ODA4MjU3fQ.Wv1eLjJiinKZ8_XD9NPqPkEKcoJ8F02mtNkXQ3GuATA"
            },
            "tests": []
        },
        {
            "_id": "b1489a14-a61b-4b70-a684-50c4db33a44f",
            "colId": "ce622ca6-536d-4f71-81ba-0a3ef36cbb55",
            "containerId": "13e3b6fa-51af-4d5c-9c3b-986ab6e05164",
            "name": "getAllOffer",
            "url": "http://localhost:3000/market",
            "method": "GET",
            "sortNum": 10000,
            "created": "2024-03-14T09:15:39.748Z",
            "modified": "2024-03-14T09:15:39.748Z",
            "headers": [
                {
                    "name": "Accept",
                    "value": "application/json"
                },
                {
                    "name": "Content-Type",
                    "value": "application/json"
                }
            ],
            "params": [],
            "auth": {
                "type": "bearer",
                "bearer": "eyJhbGciOiJIUzI1NiIsInR5cCI6IkpXVCJ9.eyJpZCI6ImJkOTk3MjAwLWRiY2UtMTFlZS1iNTEwLTM3ZmZkYTJjYTM1OSIsImlhdCI6MTcwOTgwNDY1NywiZXhwIjoxNzA5ODA4MjU3fQ.Wv1eLjJiinKZ8_XD9NPqPkEKcoJ8F02mtNkXQ3GuATA"
            },
            "tests": []
        },
        {
            "_id": "3b028442-ff88-4207-b902-e33a2d568d43",
            "colId": "ce622ca6-536d-4f71-81ba-0a3ef36cbb55",
            "containerId": "c22de10b-9f3f-4a28-a28d-568b52483553",
            "name": "getAllBuildings",
            "url": "http://localhost:3000/buildings",
            "method": "GET",
            "sortNum": 10000,
            "created": "2024-03-14T09:15:39.753Z",
            "modified": "2024-03-14T09:15:39.753Z",
            "headers": [
                {
                    "name": "Accept",
                    "value": "application/json"
                },
                {
                    "name": "Content-Type",
                    "value": "application/json"
                }
            ],
            "params": [],
            "auth": {
                "type": "bearer",
                "bearer": "eyJhbGciOiJIUzI1NiIsInR5cCI6IkpXVCJ9.eyJpZCI6ImJkOTk3MjAwLWRiY2UtMTFlZS1iNTEwLTM3ZmZkYTJjYTM1OSIsImlhdCI6MTcwOTgwNDY1NywiZXhwIjoxNzA5ODA4MjU3fQ.Wv1eLjJiinKZ8_XD9NPqPkEKcoJ8F02mtNkXQ3GuATA"
            },
            "tests": []
        },
        {
            "_id": "1b813275-916f-445e-ba65-880f240a0a58",
            "colId": "ce622ca6-536d-4f71-81ba-0a3ef36cbb55",
            "containerId": "59e75d3b-30ca-4737-81aa-b66518ab8e69",
            "name": "getTool",
            "url": "http://localhost:3000/tool",
            "method": "GET",
            "sortNum": 10000,
            "created": "2024-03-14T09:15:39.755Z",
            "modified": "2024-03-14T09:15:39.755Z",
            "headers": [
                {
                    "name": "Accept",
                    "value": "application/json"
                },
                {
                    "name": "Content-Type",
                    "value": "application/json"
                }
            ],
            "params": [],
            "auth": {
                "type": "bearer",
                "bearer": "eyJhbGciOiJIUzI1NiIsInR5cCI6IkpXVCJ9.eyJpZCI6ImJkOTk3MjAwLWRiY2UtMTFlZS1iNTEwLTM3ZmZkYTJjYTM1OSIsImlhdCI6MTcwOTg4Mzc3MCwiZXhwIjoxNzA5ODg3MzcwfQ.ySQHUbBfbfCnCAPPPxZlbd9Soz-oYv93ODZYC1NCJ0w"
            },
            "tests": []
        },
        {
            "_id": "ab596556-29ef-455f-82f0-83f5b83fba9a",
            "colId": "ce622ca6-536d-4f71-81ba-0a3ef36cbb55",
            "containerId": "d7b450d1-ef99-4331-ae6c-7c7a1015f915",
            "name": "Login",
            "url": "http://localhost:3000/user/login",
            "method": "POST",
            "sortNum": 20000,
            "created": "2024-03-14T09:15:39.730Z",
            "modified": "2024-03-14T09:15:39.730Z",
            "headers": [
                {
                    "name": "Accept",
                    "value": "application/json"
                },
                {
                    "name": "Content-Type",
                    "value": "application/json"
                }
            ],
            "params": [],
            "body": {
                "type": "json",
                "raw": "{\n  \"email\": \"teszt@teszt.hu\",\n  \"password\": \"123456789\"\n}",
                "form": []
            },
            "tests": []
        },
        {
            "_id": "dd57d77a-684d-418c-892b-e6fa95fe1e6f",
            "colId": "ce622ca6-536d-4f71-81ba-0a3ef36cbb55",
            "containerId": "03986ae3-a804-48c9-a1f9-2e6b1656addf",
            "name": "getBlockEnemies",
            "url": "http://localhost:3000/enemies/10/1",
            "method": "GET",
            "sortNum": 20000,
            "created": "2024-03-14T09:15:39.740Z",
            "modified": "2024-03-14T09:15:39.740Z",
            "headers": [
                {
                    "name": "Accept",
                    "value": "application/json"
                },
                {
                    "name": "Content-Type",
                    "value": "application/json"
                }
            ],
            "params": [],
            "auth": {
                "type": "bearer",
                "bearer": "eyJhbGciOiJIUzI1NiIsInR5cCI6IkpXVCJ9.eyJpZCI6ImJkOTk3MjAwLWRiY2UtMTFlZS1iNTEwLTM3ZmZkYTJjYTM1OSIsImlhdCI6MTcwOTgwNDY1NywiZXhwIjoxNzA5ODA4MjU3fQ.Wv1eLjJiinKZ8_XD9NPqPkEKcoJ8F02mtNkXQ3GuATA"
            },
            "tests": []
        },
        {
            "_id": "48bcd518-1100-4aeb-b360-89cf564323ee",
            "colId": "ce622ca6-536d-4f71-81ba-0a3ef36cbb55",
            "containerId": "18c3cb4b-5925-4867-9f4a-5b5272c5a4cc",
            "name": "getResidents",
            "url": "http://localhost:3000/residents/10/10",
            "method": "GET",
            "sortNum": 20000,
            "created": "2024-03-14T09:15:39.745Z",
            "modified": "2024-03-14T09:15:39.745Z",
            "headers": [
                {
                    "name": "Accept",
                    "value": "application/json"
                },
                {
                    "name": "Content-Type",
                    "value": "application/json"
                }
            ],
            "params": [],
            "auth": {
                "type": "bearer",
                "bearer": "eyJhbGciOiJIUzI1NiIsInR5cCI6IkpXVCJ9.eyJpZCI6ImJkOTk3MjAwLWRiY2UtMTFlZS1iNTEwLTM3ZmZkYTJjYTM1OSIsImlhdCI6MTcwOTgwNDY1NywiZXhwIjoxNzA5ODA4MjU3fQ.Wv1eLjJiinKZ8_XD9NPqPkEKcoJ8F02mtNkXQ3GuATA"
            },
            "tests": []
        },
        {
            "_id": "9b8bd65f-930e-49f6-be94-6fcc9742d525",
            "colId": "ce622ca6-536d-4f71-81ba-0a3ef36cbb55",
            "containerId": "13e3b6fa-51af-4d5c-9c3b-986ab6e05164",
            "name": "getAllPlayerOffer",
            "url": "http://localhost:3000/market",
            "method": "GET",
            "sortNum": 20000,
            "created": "2024-03-14T09:15:39.749Z",
            "modified": "2024-03-14T09:15:39.749Z",
            "headers": [
                {
                    "name": "Accept",
                    "value": "application/json"
                },
                {
                    "name": "Content-Type",
                    "value": "application/json"
                }
            ],
            "params": [],
            "auth": {
                "type": "bearer",
                "bearer": "eyJhbGciOiJIUzI1NiIsInR5cCI6IkpXVCJ9.eyJpZCI6ImJkOTk3MjAwLWRiY2UtMTFlZS1iNTEwLTM3ZmZkYTJjYTM1OSIsImlhdCI6MTcwOTgwNDY1NywiZXhwIjoxNzA5ODA4MjU3fQ.Wv1eLjJiinKZ8_XD9NPqPkEKcoJ8F02mtNkXQ3GuATA"
            },
            "tests": []
        },
        {
            "_id": "037042f9-11fa-4dd1-8c82-f4f18112f8ad",
            "colId": "ce622ca6-536d-4f71-81ba-0a3ef36cbb55",
            "containerId": "c22de10b-9f3f-4a28-a28d-568b52483553",
            "name": "putBuilding",
            "url": "http://localhost:3000/buildings/b275e920-dc6a-11ee-9556-414263d6e1c1",
            "method": "PUT",
            "sortNum": 20000,
            "created": "2024-03-14T09:15:39.754Z",
            "modified": "2024-03-14T09:15:39.754Z",
            "headers": [
                {
                    "name": "Accept",
                    "value": "application/json"
                },
                {
                    "name": "Content-Type",
                    "value": "application/json"
                }
            ],
            "params": [],
            "body": {
                "type": "json",
                "raw": "{\n  \"level\": 5\n}",
                "form": []
            },
            "auth": {
                "type": "bearer",
                "bearer": "eyJhbGciOiJIUzI1NiIsInR5cCI6IkpXVCJ9.eyJpZCI6ImJkOTk3MjAwLWRiY2UtMTFlZS1iNTEwLTM3ZmZkYTJjYTM1OSIsImlhdCI6MTcwOTgwNDY1NywiZXhwIjoxNzA5ODA4MjU3fQ.Wv1eLjJiinKZ8_XD9NPqPkEKcoJ8F02mtNkXQ3GuATA"
            },
            "tests": []
        },
        {
            "_id": "3e29975b-5152-4851-96cd-7ca2e7304636",
            "colId": "ce622ca6-536d-4f71-81ba-0a3ef36cbb55",
            "containerId": "59e75d3b-30ca-4737-81aa-b66518ab8e69",
            "name": "putTool",
            "url": "http://localhost:3000/tool/2c331260-dc6b-11ee-8e26-63613a671168",
            "method": "PUT",
            "sortNum": 20000,
            "created": "2024-03-14T09:15:39.756Z",
            "modified": "2024-03-14T09:15:39.756Z",
            "headers": [
                {
                    "name": "Accept",
                    "value": "application/json"
                },
                {
                    "name": "Content-Type",
                    "value": "application/json"
                }
            ],
            "params": [],
            "body": {
                "type": "json",
                "raw": "{\n  \"tool_type_id\": \"f035e679-dbba-11ee-b1e4-00155ddb1e0d\"\n}",
                "form": []
            },
            "auth": {
                "type": "bearer",
                "bearer": "eyJhbGciOiJIUzI1NiIsInR5cCI6IkpXVCJ9.eyJpZCI6ImJkOTk3MjAwLWRiY2UtMTFlZS1iNTEwLTM3ZmZkYTJjYTM1OSIsImlhdCI6MTcwOTgwNjE4OCwiZXhwIjoxNzA5ODA5Nzg4fQ.utPz_wwzjKOso9uvV7uJ-0StxeuUE94L9FcWQc2bZpg"
            },
            "tests": []
        },
        {
            "_id": "7b30ce23-4afa-4d05-b610-5d3f5e79a0c6",
            "colId": "ce622ca6-536d-4f71-81ba-0a3ef36cbb55",
            "containerId": "d7b450d1-ef99-4331-ae6c-7c7a1015f915",
            "name": "Registration",
            "url": "http://localhost:3000/user/registration",
            "method": "POST",
            "sortNum": 30000,
            "created": "2024-03-14T09:15:39.731Z",
            "modified": "2024-03-14T09:16:02.241Z",
            "headers": [
                {
                    "name": "Accept",
                    "value": "application/json"
                },
                {
                    "name": "Content-Type",
                    "value": "application/json"
                }
            ],
            "params": [],
            "body": {
                "type": "json",
                "raw": "{\n  \"name\": \"teszt\",\n  \"email\": \"teszt@teszt.hu\",\n  \"password\": \"123456789\"\n}",
                "form": []
            },
            "reqType": "post",
            "tests": []
        },
        {
            "_id": "dc375235-491d-41be-b6c6-dff15e73ece4",
            "colId": "ce622ca6-536d-4f71-81ba-0a3ef36cbb55",
            "containerId": "03986ae3-a804-48c9-a1f9-2e6b1656addf",
            "name": "postEnemy",
            "url": "http://localhost:3000/enemies",
            "method": "POST",
            "sortNum": 30000,
            "created": "2024-03-14T09:15:39.741Z",
            "modified": "2024-03-14T09:15:39.741Z",
            "headers": [
                {
                    "name": "Accept",
                    "value": "application/json"
                },
                {
                    "name": "Content-Type",
                    "value": "application/json"
                }
            ],
            "params": [],
            "body": {
                "type": "json",
                "raw": "{\n  \"objX\": 1,\n  \"objY\": 1,\n  \"blockX\": 10,\n  \"blockY\": 1,\n  \"enemy_type_id\": \"93f97947-dba8-11ee-b1e4-00155ddb1e0d\"\n}",
                "form": []
            },
            "auth": {
                "type": "bearer",
                "bearer": "eyJhbGciOiJIUzI1NiIsInR5cCI6IkpXVCJ9.eyJpZCI6ImJkOTk3MjAwLWRiY2UtMTFlZS1iNTEwLTM3ZmZkYTJjYTM1OSIsImlhdCI6MTcwOTgwNDY1NywiZXhwIjoxNzA5ODA4MjU3fQ.Wv1eLjJiinKZ8_XD9NPqPkEKcoJ8F02mtNkXQ3GuATA"
            },
            "tests": []
        },
        {
            "_id": "e19e575c-814a-47a2-8bde-4288f9b7777a",
            "colId": "ce622ca6-536d-4f71-81ba-0a3ef36cbb55",
            "containerId": "18c3cb4b-5925-4867-9f4a-5b5272c5a4cc",
            "name": "postResident",
            "url": "http://localhost:3000/residents",
            "method": "POST",
            "sortNum": 30000,
            "created": "2024-03-14T09:15:39.746Z",
            "modified": "2024-03-14T09:15:39.746Z",
            "headers": [
                {
                    "name": "Accept",
                    "value": "application/json"
                },
                {
                    "name": "Content-Type",
                    "value": "application/json"
                }
            ],
            "params": [],
            "body": {
                "type": "json",
                "raw": "{\n  \"objX\": 10,\n  \"objY\": 10,\n  \"blockX\": 10,\n  \"blockY\": 10,\n  \"resident_name\": \"Long Boo\",\n  \"profession\": \"asd\",\n  \"quest_id\": \"ac81a232-dbb6-11ee-b1e4-00155ddb1e0d\"\n}",
                "form": []
            },
            "auth": {
                "type": "bearer",
                "bearer": "eyJhbGciOiJIUzI1NiIsInR5cCI6IkpXVCJ9.eyJpZCI6ImJkOTk3MjAwLWRiY2UtMTFlZS1iNTEwLTM3ZmZkYTJjYTM1OSIsImlhdCI6MTcwOTgwNDY1NywiZXhwIjoxNzA5ODA4MjU3fQ.Wv1eLjJiinKZ8_XD9NPqPkEKcoJ8F02mtNkXQ3GuATA"
            },
            "tests": []
        },
        {
            "_id": "a289f552-00f2-472f-9193-0afc00d7df93",
            "colId": "ce622ca6-536d-4f71-81ba-0a3ef36cbb55",
            "containerId": "13e3b6fa-51af-4d5c-9c3b-986ab6e05164",
            "name": "postOffer",
            "url": "http://localhost:3000/market",
            "method": "POST",
            "sortNum": 30000,
            "created": "2024-03-14T09:15:39.750Z",
            "modified": "2024-03-14T09:15:39.750Z",
            "headers": [
                {
                    "name": "Accept",
                    "value": "application/json"
                },
                {
                    "name": "Content-Type",
                    "value": "application/json"
                }
            ],
            "params": [],
            "body": {
                "type": "json",
                "raw": "{\n  \"offeredType\": \"fa\",\n  \"offeredAmount\": 2000,\n  \"soughtType\": \"kő\",\n  \"soughtAmount\": 1000\n}",
                "form": []
            },
            "auth": {
                "type": "bearer",
                "bearer": "eyJhbGciOiJIUzI1NiIsInR5cCI6IkpXVCJ9.eyJpZCI6ImJkOTk3MjAwLWRiY2UtMTFlZS1iNTEwLTM3ZmZkYTJjYTM1OSIsImlhdCI6MTcwOTgwNDY1NywiZXhwIjoxNzA5ODA4MjU3fQ.Wv1eLjJiinKZ8_XD9NPqPkEKcoJ8F02mtNkXQ3GuATA"
            },
            "tests": []
        },
        {
            "_id": "5692169d-703d-4505-b71b-6a9c4c59c3aa",
            "colId": "ce622ca6-536d-4f71-81ba-0a3ef36cbb55",
            "containerId": "59e75d3b-30ca-4737-81aa-b66518ab8e69",
            "name": "deleteTool",
            "url": "http://localhost:3000/tool/2c331260-dc6b-11ee-8e26-63613a671168",
            "method": "DELETE",
            "sortNum": 30000,
            "created": "2024-03-14T09:15:39.757Z",
            "modified": "2024-03-14T09:15:39.757Z",
            "headers": [
                {
                    "name": "Accept",
                    "value": "application/json"
                },
                {
                    "name": "Content-Type",
                    "value": "application/json"
                }
            ],
            "params": [],
            "auth": {
                "type": "bearer",
                "bearer": "eyJhbGciOiJIUzI1NiIsInR5cCI6IkpXVCJ9.eyJpZCI6ImJkOTk3MjAwLWRiY2UtMTFlZS1iNTEwLTM3ZmZkYTJjYTM1OSIsImlhdCI6MTcwOTgwNjE4OCwiZXhwIjoxNzA5ODA5Nzg4fQ.utPz_wwzjKOso9uvV7uJ-0StxeuUE94L9FcWQc2bZpg"
            },
            "tests": []
        },
        {
            "_id": "40de6f31-9db2-4f4a-938d-7936011d6e4d",
            "colId": "ce622ca6-536d-4f71-81ba-0a3ef36cbb55",
            "containerId": "4ba0a9fc-7116-4b07-9207-72b5f183085d",
            "name": "postQuest",
            "url": "http://localhost:3000/quest",
            "method": "POST",
            "sortNum": 30000,
            "created": "2024-03-14T09:15:39.759Z",
            "modified": "2024-03-14T10:02:41.955Z",
            "headers": [
                {
                    "name": "Accept",
                    "value": "application/json"
                },
                {
                    "name": "Content-Type",
                    "value": "application/json"
                }
            ],
            "params": [],
            "body": {
                "type": "json",
                "raw": "{\n  \"quest_id\": \"81c5073d-e1da-11ee-b1e4-00155ddb1e0d\"\n}",
                "form": []
            },
            "reqType": "post",
            "auth": {
                "type": "bearer",
                "bearer": "eyJhbGciOiJIUzI1NiIsInR5cCI6IkpXVCJ9.eyJpZCI6IjI5MThiYTIwLWUxZTktMTFlZS1hYWJiLWIxNWIxZTAyYTRhNiIsImlhdCI6MTcxMDQxMDIwNCwiZXhwIjoxNzEwNDEzODA0fQ.azv7RIGn4trrwD4kxdkjwVA6yaumBh8ElsSDB_GZsCM"
            },
            "tests": []
        },
        {
            "_id": "a0102b6e-fd03-4a3c-b778-318394f174dd",
            "colId": "ce622ca6-536d-4f71-81ba-0a3ef36cbb55",
            "containerId": "c22de10b-9f3f-4a28-a28d-568b52483553",
            "name": "deleteBuilding",
            "url": "http://localhost:3000/buildings/b275e920-dc6a-11ee-9556-414263d6e1c1",
            "method": "DELETE",
            "sortNum": 30000,
            "created": "2024-03-14T09:15:39.763Z",
            "modified": "2024-03-14T09:15:39.763Z",
            "headers": [
                {
                    "name": "Accept",
                    "value": "application/json"
                },
                {
                    "name": "Content-Type",
                    "value": "application/json"
                }
            ],
            "params": [],
            "auth": {
                "type": "bearer",
                "bearer": "eyJhbGciOiJIUzI1NiIsInR5cCI6IkpXVCJ9.eyJpZCI6ImJkOTk3MjAwLWRiY2UtMTFlZS1iNTEwLTM3ZmZkYTJjYTM1OSIsImlhdCI6MTcwOTgwNjE4OCwiZXhwIjoxNzA5ODA5Nzg4fQ.utPz_wwzjKOso9uvV7uJ-0StxeuUE94L9FcWQc2bZpg"
            },
            "tests": []
        },
        {
            "_id": "569f2a57-a3af-4b1f-8ec1-3eade993f6a3",
            "colId": "ce622ca6-536d-4f71-81ba-0a3ef36cbb55",
            "containerId": "d7b450d1-ef99-4331-ae6c-7c7a1015f915",
            "name": "PutUser",
            "url": "http://localhost:3000/user",
            "method": "PUT",
            "sortNum": 40000,
            "created": "2024-03-14T09:15:39.732Z",
            "modified": "2024-03-14T09:15:39.732Z",
            "headers": [
                {
                    "name": "Accept",
                    "value": "application/json"
                },
                {
                    "name": "Content-Type",
                    "value": "application/json"
                }
            ],
            "params": [],
            "body": {
                "type": "json",
                "raw": "{\n  \"player_name\": \"teszt\",\n  \"email\": \"teszt@teszt.hu\",\n  \"password\": \"123456789\"\n}",
                "form": []
            },
            "auth": {
                "type": "bearer",
                "bearer": "eyJhbGciOiJIUzI1NiIsInR5cCI6IkpXVCJ9.eyJpZCI6ImJkOTk3MjAwLWRiY2UtMTFlZS1iNTEwLTM3ZmZkYTJjYTM1OSIsImlhdCI6MTcwOTg4MjAwOCwiZXhwIjoxNzA5ODg1NjA4fQ.U8pnyseFIr59e-ut2C9WNGxztyV37lkOBXTHiyotgMs"
            },
            "tests": []
        },
        {
            "_id": "5accbeb3-5e46-4379-a1fb-f4ac2297149e",
            "colId": "ce622ca6-536d-4f71-81ba-0a3ef36cbb55",
            "containerId": "95b450e7-cbec-4a87-b49a-7b75ded22a02",
            "name": "getInventory",
            "url": "http://localhost:3000/player/inventory",
            "method": "GET",
            "sortNum": 40000,
            "created": "2024-03-14T09:15:39.736Z",
            "modified": "2024-03-14T09:15:39.736Z",
            "headers": [
                {
                    "name": "Accept",
                    "value": "application/json"
                },
                {
                    "name": "Content-Type",
                    "value": "application/json"
                }
            ],
            "params": [],
            "auth": {
                "type": "bearer",
                "bearer": "eyJhbGciOiJIUzI1NiIsInR5cCI6IkpXVCJ9.eyJpZCI6ImJkOTk3MjAwLWRiY2UtMTFlZS1iNTEwLTM3ZmZkYTJjYTM1OSIsImlhdCI6MTcwOTgwNDMwMiwiZXhwIjoxNzA5ODA3OTAyfQ.rswMGATMIuV5XAoBpFqPjdbVqu-PPlHaNcSpaQ_qK2s"
            },
            "tests": []
        },
        {
            "_id": "fababa69-1b59-4dad-80d1-7e5d4feb8bb0",
            "colId": "ce622ca6-536d-4f71-81ba-0a3ef36cbb55",
            "containerId": "03986ae3-a804-48c9-a1f9-2e6b1656addf",
            "name": "putEnemy",
            "url": "http://localhost:3000/enemies/491725a0-dc67-11ee-8eca-6bdb1578bc48",
            "method": "PUT",
            "sortNum": 40000,
            "created": "2024-03-14T09:15:39.742Z",
            "modified": "2024-03-14T09:15:39.742Z",
            "headers": [
                {
                    "name": "Accept",
                    "value": "application/json"
                },
                {
                    "name": "Content-Type",
                    "value": "application/json"
                }
            ],
            "params": [],
            "body": {
                "type": "json",
                "raw": "{\n  \"objX\": 10,\n  \"objY\": 10,\n  \"blockX\": 10,\n  \"blockY\": 10,\n  \"HP\": 99\n}",
                "form": []
            },
            "auth": {
                "type": "bearer",
                "bearer": "eyJhbGciOiJIUzI1NiIsInR5cCI6IkpXVCJ9.eyJpZCI6ImJkOTk3MjAwLWRiY2UtMTFlZS1iNTEwLTM3ZmZkYTJjYTM1OSIsImlhdCI6MTcwOTgwNDY1NywiZXhwIjoxNzA5ODA4MjU3fQ.Wv1eLjJiinKZ8_XD9NPqPkEKcoJ8F02mtNkXQ3GuATA"
            },
            "tests": []
        },
        {
            "_id": "3108907e-df99-4357-ba77-b1767354c7fb",
            "colId": "ce622ca6-536d-4f71-81ba-0a3ef36cbb55",
            "containerId": "18c3cb4b-5925-4867-9f4a-5b5272c5a4cc",
            "name": "putResident",
            "url": "http://localhost:3000/residents/18a24ab0-dc69-11ee-9c12-0984faf6ab7f",
            "method": "PUT",
            "sortNum": 40000,
            "created": "2024-03-14T09:15:39.747Z",
            "modified": "2024-03-14T09:15:39.747Z",
            "headers": [
                {
                    "name": "Accept",
                    "value": "application/json"
                },
                {
                    "name": "Content-Type",
                    "value": "application/json"
                }
            ],
            "params": [],
            "body": {
                "type": "json",
                "raw": "{\n  \"objX\": 3,\n  \"objY\": 3,\n  \"blockX\": 10,\n  \"blockY\": 10,\n  \"resident_name\": \"Long Boo3\",\n  \"profession\": \"asddsa\",\n  \"quest_id\": \"712cc5fb-dc5a-11ee-b1e4-00155ddb1e0d\"\n}",
                "form": []
            },
            "auth": {
                "type": "bearer",
                "bearer": "eyJhbGciOiJIUzI1NiIsInR5cCI6IkpXVCJ9.eyJpZCI6ImJkOTk3MjAwLWRiY2UtMTFlZS1iNTEwLTM3ZmZkYTJjYTM1OSIsImlhdCI6MTcwOTgwNDY1NywiZXhwIjoxNzA5ODA4MjU3fQ.Wv1eLjJiinKZ8_XD9NPqPkEKcoJ8F02mtNkXQ3GuATA"
            },
            "tests": []
        },
        {
            "_id": "7dd46919-a93a-4edc-b8e8-4f68d7618018",
            "colId": "ce622ca6-536d-4f71-81ba-0a3ef36cbb55",
            "containerId": "13e3b6fa-51af-4d5c-9c3b-986ab6e05164",
            "name": "putOffer",
            "url": "http://localhost:3000/market/0b3b16d0-dc6a-11ee-93c8-35723869a41c",
            "method": "PUT",
            "sortNum": 40000,
            "created": "2024-03-14T09:15:39.751Z",
            "modified": "2024-03-14T09:15:39.751Z",
            "headers": [
                {
                    "name": "Accept",
                    "value": "application/json"
                },
                {
                    "name": "Content-Type",
                    "value": "application/json"
                }
            ],
            "params": [],
            "body": {
                "type": "json",
                "raw": "{\n  \"offeredType\": \"fa\",\n  \"offeredAmount\": 5000,\n  \"soughtType\": \"kő\",\n  \"soughtAmount\": 5000\n}",
                "form": []
            },
            "auth": {
                "type": "bearer",
                "bearer": "eyJhbGciOiJIUzI1NiIsInR5cCI6IkpXVCJ9.eyJpZCI6ImJkOTk3MjAwLWRiY2UtMTFlZS1iNTEwLTM3ZmZkYTJjYTM1OSIsImlhdCI6MTcwOTgwNDY1NywiZXhwIjoxNzA5ODA4MjU3fQ.Wv1eLjJiinKZ8_XD9NPqPkEKcoJ8F02mtNkXQ3GuATA"
            },
            "tests": []
        },
        {
            "_id": "5199c390-da48-4ba5-b6ec-afc74413605f",
            "colId": "ce622ca6-536d-4f71-81ba-0a3ef36cbb55",
            "containerId": "59e75d3b-30ca-4737-81aa-b66518ab8e69",
            "name": "postTool",
            "url": "http://localhost:3000/tool",
            "method": "POST",
            "sortNum": 40000,
            "created": "2024-03-14T09:15:39.758Z",
            "modified": "2024-03-14T09:15:39.758Z",
            "headers": [
                {
                    "name": "Accept",
                    "value": "application/json"
                },
                {
                    "name": "Content-Type",
                    "value": "application/json"
                }
            ],
            "params": [],
            "body": {
                "type": "json",
                "raw": "{\n  \"tool_type_id\": \"6c20b405-dbbb-11ee-b1e4-00155ddb1e0d\"\n}",
                "form": []
            },
            "auth": {
                "type": "bearer",
                "bearer": "eyJhbGciOiJIUzI1NiIsInR5cCI6IkpXVCJ9.eyJpZCI6ImJkOTk3MjAwLWRiY2UtMTFlZS1iNTEwLTM3ZmZkYTJjYTM1OSIsImlhdCI6MTcwOTgwNjE4OCwiZXhwIjoxNzA5ODA5Nzg4fQ.utPz_wwzjKOso9uvV7uJ-0StxeuUE94L9FcWQc2bZpg"
            },
            "tests": []
        },
        {
            "_id": "abdbbe9a-0dd2-4516-a62c-edbdc448e831",
            "colId": "ce622ca6-536d-4f71-81ba-0a3ef36cbb55",
            "containerId": "4ba0a9fc-7116-4b07-9207-72b5f183085d",
            "name": "putQuest",
            "url": "http://localhost:3000/quest/ac81a232-dbb6-11ee-b1e4-00155ddb1e0d",
            "method": "PUT",
            "sortNum": 40000,
            "created": "2024-03-14T09:15:39.760Z",
            "modified": "2024-03-14T09:15:39.760Z",
            "headers": [
                {
                    "name": "Accept",
                    "value": "application/json"
                },
                {
                    "name": "Content-Type",
                    "value": "application/json"
                }
            ],
            "params": [],
            "body": {
                "type": "json",
                "raw": "{\n  \"is_completed\": 1,\n  \"is_active\": 1,\n  \"currentProgress\": 2000,\n  \"targetProgress\": 2000\n}",
                "form": []
            },
            "auth": {
                "type": "bearer",
                "bearer": "eyJhbGciOiJIUzI1NiIsInR5cCI6IkpXVCJ9.eyJpZCI6ImJkOTk3MjAwLWRiY2UtMTFlZS1iNTEwLTM3ZmZkYTJjYTM1OSIsImlhdCI6MTcwOTgwNjE4OCwiZXhwIjoxNzA5ODA5Nzg4fQ.utPz_wwzjKOso9uvV7uJ-0StxeuUE94L9FcWQc2bZpg"
            },
            "tests": []
        },
        {
            "_id": "da20986f-84ff-49bb-ac15-d0d5dcfc120f",
            "colId": "ce622ca6-536d-4f71-81ba-0a3ef36cbb55",
            "containerId": "c22de10b-9f3f-4a28-a28d-568b52483553",
            "name": "postBuilding",
            "url": "http://localhost:3000/buildings",
            "method": "POST",
            "sortNum": 40000,
            "created": "2024-03-14T09:15:39.764Z",
            "modified": "2024-03-14T09:15:39.764Z",
            "headers": [
                {
                    "name": "Accept",
                    "value": "application/json"
                },
                {
                    "name": "Content-Type",
                    "value": "application/json"
                }
            ],
            "params": [],
            "body": {
                "type": "json",
                "raw": "{\n  \"building_type_id\": \"2bbd092a-dbba-11ee-b1e4-00155ddb1e0d\"\n}",
                "form": []
            },
            "auth": {
                "type": "bearer",
                "bearer": "eyJhbGciOiJIUzI1NiIsInR5cCI6IkpXVCJ9.eyJpZCI6ImJkOTk3MjAwLWRiY2UtMTFlZS1iNTEwLTM3ZmZkYTJjYTM1OSIsImlhdCI6MTcwOTgwNDY1NywiZXhwIjoxNzA5ODA4MjU3fQ.Wv1eLjJiinKZ8_XD9NPqPkEKcoJ8F02mtNkXQ3GuATA"
            },
            "tests": []
        },
        {
            "_id": "b5591bf4-fbf1-4c05-9d56-694852b814e7",
            "colId": "ce622ca6-536d-4f71-81ba-0a3ef36cbb55",
            "containerId": "95b450e7-cbec-4a87-b49a-7b75ded22a02",
            "name": "putPlayer",
            "url": "http://localhost:3000/player",
            "method": "PUT",
            "sortNum": 50000,
            "created": "2024-03-14T09:15:39.737Z",
            "modified": "2024-03-14T09:15:39.737Z",
            "headers": [
                {
                    "name": "Accept",
                    "value": "application/json"
                },
                {
                    "name": "Content-Type",
                    "value": "application/json"
                }
            ],
            "params": [],
            "body": {
                "type": "json",
                "raw": "{\n  \"player_name\": \"Mihaly\",\n  \"money\": 1000,\n  \"world_name\": \"First\",\n  \"stone\": 5000,\n  \"wood\": 200,\n  \"coal\": 200,\n  \"iron\": 200,\n  \"wheat\": 200,\n  \"fish\": 200,\n  \"objX\": 10,\n  \"objY\": 10,\n  \"blockX\": 10,\n  \"blockY\": 10\n}",
                "form": []
            },
            "auth": {
                "type": "bearer",
                "bearer": "eyJhbGciOiJIUzI1NiIsInR5cCI6IkpXVCJ9.eyJpZCI6ImJkOTk3MjAwLWRiY2UtMTFlZS1iNTEwLTM3ZmZkYTJjYTM1OSIsImlhdCI6MTcwOTg4MjAwOCwiZXhwIjoxNzA5ODg1NjA4fQ.U8pnyseFIr59e-ut2C9WNGxztyV37lkOBXTHiyotgMs"
            },
            "tests": []
        },
        {
            "_id": "8663764a-8da8-4225-8b33-fe8e83d9a043",
            "colId": "ce622ca6-536d-4f71-81ba-0a3ef36cbb55",
            "containerId": "03986ae3-a804-48c9-a1f9-2e6b1656addf",
            "name": "deleteEnemy",
            "url": "http://localhost:3000/enemies/491725a0-dc67-11ee-8eca-6bdb1578bc48",
            "method": "DELETE",
            "sortNum": 50000,
            "created": "2024-03-14T09:15:39.743Z",
            "modified": "2024-03-14T09:15:39.743Z",
            "headers": [
                {
                    "name": "Accept",
                    "value": "application/json"
                },
                {
                    "name": "Content-Type",
                    "value": "application/json"
                }
            ],
            "params": [],
            "auth": {
                "type": "bearer",
                "bearer": "eyJhbGciOiJIUzI1NiIsInR5cCI6IkpXVCJ9.eyJpZCI6ImJkOTk3MjAwLWRiY2UtMTFlZS1iNTEwLTM3ZmZkYTJjYTM1OSIsImlhdCI6MTcwOTgwNDY1NywiZXhwIjoxNzA5ODA4MjU3fQ.Wv1eLjJiinKZ8_XD9NPqPkEKcoJ8F02mtNkXQ3GuATA"
            },
            "tests": []
        },
        {
            "_id": "06da3819-7c4a-46c3-b1e8-02e3e5a63276",
            "colId": "ce622ca6-536d-4f71-81ba-0a3ef36cbb55",
            "containerId": "13e3b6fa-51af-4d5c-9c3b-986ab6e05164",
            "name": "deleteOffer",
            "url": "http://localhost:3000/market/0b3b16d0-dc6a-11ee-93c8-35723869a41c",
            "method": "DELETE",
            "sortNum": 50000,
            "created": "2024-03-14T09:15:39.752Z",
            "modified": "2024-03-14T09:15:39.752Z",
            "headers": [
                {
                    "name": "Accept",
                    "value": "application/json"
                },
                {
                    "name": "Content-Type",
                    "value": "application/json"
                }
            ],
            "params": [],
            "auth": {
                "type": "bearer",
                "bearer": "eyJhbGciOiJIUzI1NiIsInR5cCI6IkpXVCJ9.eyJpZCI6ImJkOTk3MjAwLWRiY2UtMTFlZS1iNTEwLTM3ZmZkYTJjYTM1OSIsImlhdCI6MTcwOTgwNDY1NywiZXhwIjoxNzA5ODA4MjU3fQ.Wv1eLjJiinKZ8_XD9NPqPkEKcoJ8F02mtNkXQ3GuATA"
            },
            "tests": []
        },
        {
            "_id": "b236f096-c038-42c5-ac04-651b468acff0",
            "colId": "ce622ca6-536d-4f71-81ba-0a3ef36cbb55",
            "containerId": "4ba0a9fc-7116-4b07-9207-72b5f183085d",
            "name": "deleteQuest",
            "url": "http://localhost:3000/quest/ac81a232-dbb6-11ee-b1e4-00155ddb1e0d",
            "method": "DELETE",
            "sortNum": 50000,
            "created": "2024-03-14T09:15:39.761Z",
            "modified": "2024-03-14T09:15:39.761Z",
            "headers": [
                {
                    "name": "Accept",
                    "value": "application/json"
                },
                {
                    "name": "Content-Type",
                    "value": "application/json"
                }
            ],
            "params": [],
            "auth": {
                "type": "bearer",
                "bearer": "eyJhbGciOiJIUzI1NiIsInR5cCI6IkpXVCJ9.eyJpZCI6ImJkOTk3MjAwLWRiY2UtMTFlZS1iNTEwLTM3ZmZkYTJjYTM1OSIsImlhdCI6MTcwOTgwNjE4OCwiZXhwIjoxNzA5ODA5Nzg4fQ.utPz_wwzjKOso9uvV7uJ-0StxeuUE94L9FcWQc2bZpg"
            },
            "tests": []
        },
        {
            "_id": "14aef57c-e06d-45e7-bb99-db0896a21e9f",
            "colId": "ce622ca6-536d-4f71-81ba-0a3ef36cbb55",
            "containerId": "18c3cb4b-5925-4867-9f4a-5b5272c5a4cc",
            "name": "deleteResident",
            "url": "http://localhost:3000/residents/18a24ab0-dc69-11ee-9c12-0984faf6ab7f",
            "method": "DELETE",
            "sortNum": 50000,
            "created": "2024-03-14T09:15:39.762Z",
            "modified": "2024-03-14T09:15:39.762Z",
            "headers": [
                {
                    "name": "Accept",
                    "value": "application/json"
                },
                {
                    "name": "Content-Type",
                    "value": "application/json"
                }
            ],
            "params": [],
            "auth": {
                "type": "bearer",
                "bearer": "eyJhbGciOiJIUzI1NiIsInR5cCI6IkpXVCJ9.eyJpZCI6ImJkOTk3MjAwLWRiY2UtMTFlZS1iNTEwLTM3ZmZkYTJjYTM1OSIsImlhdCI6MTcwOTgwNDY1NywiZXhwIjoxNzA5ODA4MjU3fQ.Wv1eLjJiinKZ8_XD9NPqPkEKcoJ8F02mtNkXQ3GuATA"
            },
            "tests": []
        },
        {
            "_id": "a07c64d9-bf87-436f-8533-8baed718f627",
            "colId": "ce622ca6-536d-4f71-81ba-0a3ef36cbb55",
            "containerId": "95b450e7-cbec-4a87-b49a-7b75ded22a02",
            "name": "deletePlayer",
            "url": "http://localhost:3000/player",
            "method": "DELETE",
            "sortNum": 60000,
            "created": "2024-03-14T09:15:39.738Z",
            "modified": "2024-03-14T09:15:39.738Z",
            "headers": [
                {
                    "name": "Accept",
                    "value": "application/json"
                },
                {
                    "name": "Content-Type",
                    "value": "application/json"
                }
            ],
            "params": [],
            "auth": {
                "type": "bearer",
                "bearer": "eyJhbGciOiJIUzI1NiIsInR5cCI6IkpXVCJ9.eyJpZCI6IjZhMTQ2MzQwLWRjNjYtMTFlZS1iM2MxLWFkZmIzYTdmMWUyOSIsImlhdCI6MTcwOTgwNDQ0MCwiZXhwIjoxNzA5ODA4MDQwfQ.zKthOO-HYVlG2TI0d41mWJoTLU_vDqwYrUazvl6qOfg"
            },
            "tests": []
        }
    ]
}